pyqt_find_text_widget/__init__.py
pyqt_find_text_widget/findTextWidget.py
pyqt_find_text_widget/ico/__init__.py
pyqt_find_text_widget/ico/case.svg
pyqt_find_text_widget/ico/close.svg
pyqt_find_text_widget/ico/next.svg
pyqt_find_text_widget/ico/prev.svg
pyqt_find_text_widget/ico/regex.svg
pyqt_find_text_widget/ico/word.svg
pyqt_find_text_widget-0.0.12.dist-info/LICENSE
pyqt_find_text_widget-0.0.12.dist-info/METADATA
pyqt_find_text_widget-0.0.12.dist-info/WHEEL
pyqt_find_text_widget-0.0.12.dist-info/top_level.txt
pyqt_find_text_widget-0.0.12.dist-info/RECORD
