Metadata-Version: 2.1
Name: pyqt-find-text-widget
Version: 0.0.12
Summary: PyQt widget which can be used to find text in QTextEdit/QTextBrowser
Home-page: https://github.com/yjg30737/pyqt-find-text-widget.git
Author: Jung Gyu Yoon
Author-email: yjg30737@gmail.com
License: MIT
License-File: LICENSE
Requires-Dist: PyQt5 (>=5.8)
Requires-Dist: pyqt-svg-button (>=0.0.1)
